LICENSE
MANIFEST.in
README.md
requirements.txt
setup.py
permsc/__init__.py
permsc/_version.py
permsc/data.py
permsc/types.py
permsc.egg-info/PKG-INFO
permsc.egg-info/SOURCES.txt
permsc.egg-info/dependency_links.txt
permsc.egg-info/requires.txt
permsc.egg-info/top_level.txt
permsc/aggregator/__init__.py
permsc/aggregator/approximate.py
permsc/aggregator/base.py
permsc/aggregator/exact.py
permsc/aggregator/utils.py
permsc/llm/__init__.py
permsc/llm/openai_pool.py
permsc/llm/prompt_builder.py
permsc/llm/prompt_pipeline.py
permsc/llm/utils.py