Metadata-Version: 2.1
Name: permsc
Version: 0.0.2
Summary: Official codebase for permutation self-consistency.
Home-page: https://github.com/castorini/perm-sc
Author: Raphael Tang
Author-email: r33tang@uwaterloo.ca
License: MIT
Requires-Python: >=3.10
License-File: LICENSE
